tabbyset/__init__.py
tabbyset/__legacy__/__init__.py
tabbyset/__legacy__/file_formats/__init__.py
tabbyset/__legacy__/file_formats/v1/__init__.py
tabbyset/__legacy__/file_formats/v1/abc/__init__.py
tabbyset/__legacy__/file_formats/v1/abc/abstract_test_cases_reader.py
tabbyset/__legacy__/file_formats/v1/csv1/__init__.py
tabbyset/__legacy__/file_formats/v1/csv1/reader.py
tabbyset/__legacy__/file_formats/v1/csv1/writer.py
tabbyset/db/__init__.py
tabbyset/db/id_utils.py
tabbyset/db/tests_tracker.py
tabbyset/entities/__init__.py
tabbyset/entities/test_case.py
tabbyset/entities/test_script.py
tabbyset/file_formats/__init__.py
tabbyset/file_formats/constants.py
tabbyset/file_formats/exceptions.py
tabbyset/file_formats/glob_patterns.py
tabbyset/file_formats/abc/__init__.py
tabbyset/file_formats/abc/abstract_test_cases_reader.py
tabbyset/file_formats/abc/abstract_test_cases_writer.py
tabbyset/file_formats/abc/source_io.py
tabbyset/file_formats/common/__init__.py
tabbyset/file_formats/common/parsing_logger.py
tabbyset/file_formats/common/reader.py
tabbyset/file_formats/common/multiheader_csv/__init__.py
tabbyset/file_formats/common/multiheader_csv/config.py
tabbyset/file_formats/common/multiheader_csv/core.py
tabbyset/file_formats/common/multiheader_csv/utils.py
tabbyset/file_formats/csv1/__init__.py
tabbyset/file_formats/csv1/reader.py
tabbyset/file_formats/csv1/writer.py
tabbyset/file_formats/csv2/__init__.py
tabbyset/file_formats/csv2/reader.py
tabbyset/file_formats/csv2/writer.py
tabbyset/file_formats/multiheader_csv/__init__.py
tabbyset/file_formats/multiheader_csv/reader.py
tabbyset/file_formats/multiheader_csv/writer.py
tabbyset/file_formats/tc_jsonl/__init__.py
tabbyset/file_formats/tc_jsonl/read_jsonl_testcase.py
tabbyset/file_formats/tc_jsonl/writer.py
tabbyset/file_formats/tcs_jsonl/__init__.py
tabbyset/file_formats/tcs_jsonl/reader.py
tabbyset/file_formats/tcs_jsonl/tc_to_dict.py
tabbyset/file_formats/tcs_jsonl/writer.py
tabbyset/presets/__init__.py
tabbyset-1.0.2.dist-info/licenses/LICENSE
tabbyset-1.0.2.dist-info/METADATA
tabbyset-1.0.2.dist-info/WHEEL
tabbyset-1.0.2.dist-info/top_level.txt
tabbyset-1.0.2.dist-info/RECORD
