Metadata-Version: 2.4
Name: tabbyset
Version: 1.0.2
Summary: Exactpro basic tooling for working with tests proprietary files
License-Expression: Apache-2.0
Requires-Python: >=3.9
License-File: LICENSE
Requires-Dist: tqdm>=4.0.0
Dynamic: license-file
